LICENSE
MANIFEST.in
README.rst
setup.py
django_ohm2_currencies_light.egg-info/PKG-INFO
django_ohm2_currencies_light.egg-info/SOURCES.txt
django_ohm2_currencies_light.egg-info/dependency_links.txt
django_ohm2_currencies_light.egg-info/requires.txt
django_ohm2_currencies_light.egg-info/top_level.txt
docs/INFO.txt
ohm2_currencies_light/__init__.py
ohm2_currencies_light/admin.py
ohm2_currencies_light/apps.py
ohm2_currencies_light/context_processors.py
ohm2_currencies_light/decorators.py
ohm2_currencies_light/definitions.py
ohm2_currencies_light/dispatcher.py
ohm2_currencies_light/errors.py
ohm2_currencies_light/managers.py
ohm2_currencies_light/middlewares.py
ohm2_currencies_light/models.py
ohm2_currencies_light/serializers.py
ohm2_currencies_light/settings.py
ohm2_currencies_light/tests.py
ohm2_currencies_light/urls.py
ohm2_currencies_light/utils.py
ohm2_currencies_light/views.py
ohm2_currencies_light/management/__init__.py
ohm2_currencies_light/management/__pycache__/__init__.cpython-35.pyc
ohm2_currencies_light/management/commands/__init__.py
ohm2_currencies_light/management/commands/ohm2_currencies_light_init.py
ohm2_currencies_light/management/commands/ohm2_currencies_light_test_command.py
ohm2_currencies_light/management/commands/__pycache__/__init__.cpython-35.pyc
ohm2_currencies_light/management/commands/__pycache__/ohm2_currencies_light_init.cpython-35.pyc
ohm2_currencies_light/migrations/0001_initial.py
ohm2_currencies_light/migrations/0002_auto_20181119_2052.py
ohm2_currencies_light/migrations/0003_auto_20190913_1929.py
ohm2_currencies_light/migrations/__init__.py
ohm2_currencies_light/migrations/__pycache__/0001_initial.cpython-35.pyc
ohm2_currencies_light/migrations/__pycache__/0002_auto_20181119_2052.cpython-35.pyc
ohm2_currencies_light/migrations/__pycache__/__init__.cpython-35.pyc